midi2voice/__init__.py
midi2voice/__main__.py
midi2voice/lyrics_tokenizer.py
midi2voice/midi2xml.py
midi2voice-1.0.4.dist-info/LICENSE
midi2voice-1.0.4.dist-info/METADATA
midi2voice-1.0.4.dist-info/WHEEL
midi2voice-1.0.4.dist-info/top_level.txt
midi2voice-1.0.4.dist-info/RECORD
