Metadata-Version: 2.1
Name: midi2voice
Version: 1.0.4
Summary: Singing synthesis from MIDI file
Home-page: https://github.com/mathigatti/midi2voice
Author: Mathias Gatti
Author-email: mathigatti@gmail.com
License: UNKNOWN
Platform: UNKNOWN
Classifier: Programming Language :: Python :: 3
Classifier: License :: OSI Approved :: MIT License
Classifier: Operating System :: OS Independent
Requires-Python: >=3.6
License-File: LICENSE
Requires-Dist: requests
Requires-Dist: music21
Requires-Dist: Pyphen
